{
  "name": "meteors",
  "type": "component",
  "description": "A meteor shower effect.",
  "category": "animations",
  "dependencies": [],
  "files": [],
  "meta": {
    "tags": ["animation"]
  },
  "props": [
    { "name": "number", "type": "number", "default": "20", "description": "Number of meteors to render" },
    { "name": "minDelay", "type": "number", "default": "0.2", "description": "Minimum animation delay in seconds" },
    { "name": "maxDelay", "type": "number", "default": "1.2", "description": "Maximum animation delay in seconds" },
    { "name": "minDuration", "type": "number", "default": "2", "description": "Minimum animation duration in seconds" },
    { "name": "maxDuration", "type": "number", "default": "10", "description": "Maximum animation duration in seconds" },
    { "name": "angle", "type": "number", "default": "215", "description": "Angle of the meteor trail in degrees" },
    { "name": "className", "type": "string", "default": "-", "description": "Additional CSS classes for each meteor" }
  ]
}
